dhruv_package/__init__.py
dhruv_package/main.py
dhruv_package-0.1.dist-info/METADATA
dhruv_package-0.1.dist-info/WHEEL
dhruv_package-0.1.dist-info/top_level.txt
dhruv_package-0.1.dist-info/RECORD
